count16.v
module count16(clk, reset, out);
  input clk, reset;
  output[3:0] out;

  reg[3:0] out;

  always @ (posedge clk or negedge reset)
    begin
      if (reset)
        out <= 4'b0000;
      else
        out <= out + 4'b0001;
    end


endmodule

count16_test.v
module count16_test;
  reg clk;
  reg reset;
  wire [3:0] out;


  count16 u_count16(
            .clk   	(clk    ),
            .reset 	(reset  ),
            .out   	(out    )
          );

  // 產生 10ns 週期的時脈：高5ns、低5ns
  initial
    begin
      clk = 0;
      forever
        #5 clk = ~clk;
    end

  // 控制 reset 並觀察 out 變化
  initial
    begin
      // 初始化
      reset = 1;    // 先 reset
      #12;          // 等待 12ns

      reset = 0;    // 放開 reset，開始計數
      #100;         // 模擬一段時間

      reset = 1;    // 再 reset 一次
      #10;

      reset = 0;    // 繼續計數
      #40;

      $finish;      // 結束模擬
    end

  initial
    begin
      $dumpfile("count16_wave.vcd");         // 指定輸出的波形檔名
      $dumpvars(0, count16_test);  // 記錄整個模組所有變數
    end

endmodule

count16_wave.vcd
$date
	Sat May 17 10:48:28 2025
$end
$version
	Icarus Verilog
$end
$timescale
	1s
$end
$scope module count16_test $end
$var wire 4 ! out [3:0] $end
$var reg 1 " clk $end
$var reg 1 # reset $end
$scope module u_count16 $end
$var wire 1 " clk $end
$var wire 1 # reset $end
$var reg 4 $ out [3:0] $end
$upscope $end
$upscope $end
$enddefinitions $end
$comment Show the parameter values. $end
$dumpall
$end
#0
$dumpvars
bx $
1#
0"
bx !
$end
#5
b0 !
b0 $
1"
#10
0"
#12
b1 !
b1 $
0#
#15
b10 !
b10 $
1"
#20
0"
#25
b11 !
b11 $
1"
#30
0"
#35
b100 !
b100 $
1"
#40
0"
#45
b101 !
b101 $
1"
#50
0"
#55
b110 !
b110 $
1"
#60
0"
#65
b111 !
b111 $
1"
#70
0"
#75
b1000 !
b1000 $
1"
#80
0"
#85
b1001 !
b1001 $
1"
#90
0"
#95
b1010 !
b1010 $
1"
#100
0"
#105
b1011 !
b1011 $
1"
#110
0"
#112
1#
#115
b0 !
b0 $
1"
#120
0"
#122
b1 !
b1 $
0#
#125
b10 !
b10 $
1"
#130
0"
#135
b11 !
b11 $
1"
#140
0"
#145
b100 !
b100 $
1"
#150
0"
#155
b101 !
b101 $
1"
