diff.v
module diff(clk, reset, d, q);
  input clk, reset;
  input [4:0] d;
  output reg [4:0] q;

  // 非同步、低電位有效的 reset
  always @(posedge clk or negedge reset)
    if (!reset)
      q <= 0;
    else
      q <= d;
endmodule

diff_test.v
`timescale 1ns/1ps

module diff_test;
  reg clk, reset;
  reg [4:0] d;
  wire [4:0] q;

  // 實例化模組
  diff u_diff (
    .clk(clk),
    .reset(reset),
    .d(d),
    .q(q)
  );

  // 時脈產生器：20ns 一個週期
  initial begin
    clk = 0;
    forever #10 clk = ~clk;
  end

  // reset 流程
  initial begin
    reset = 0;    // 先 reset（active-low）
    #15 reset = 1; // 放開 reset
  end

  // 輸入 d 隨時間變化
  initial begin
    d = 5;
    #20 d = 6;
    #20 d = 8;
    #20 d = 15;
    #20 d = 3;
    #20 $finish;
  end

  // 顯示波形資訊
  initial begin
    $monitor("Time=%0t | clk=%b | reset=%b | d=%b | q=%b", $time, clk, reset, d, q);
  end

  // 波形檔案輸出
  initial begin
    $dumpfile("diff_wave.vcd");
    $dumpvars(0, diff_test);
  end
endmodule

diff_wave.vcd
$date
	Sat May 17 16:43:46 2025
$end
$version
	Icarus Verilog
$end
$timescale
	1ps
$end
$scope module diff_test $end
$var wire 5 ! q [4:0] $end
$var reg 1 " clk $end
$var reg 5 # d [4:0] $end
$var reg 1 $ reset $end
$scope module u_diff $end
$var wire 1 " clk $end
$var wire 5 % d [4:0] $end
$var wire 1 $ reset $end
$var reg 5 & q [4:0] $end
$upscope $end
$upscope $end
$enddefinitions $end
$comment Show the parameter values. $end
$dumpall
$end
#0
$dumpvars
b0 &
b101 %
0$
b101 #
0"
b0 !
$end
#10000
1"
#15000
1$
#20000
0"
b110 #
b110 %
#30000
b110 !
b110 &
1"
#40000
0"
b1000 #
b1000 %
#50000
b1000 !
b1000 &
1"
#60000
0"
b1111 #
b1111 %
#70000
b1111 !
b1111 &
1"
#80000
0"
b11 #
b11 %
#90000
b11 !
b11 &
1"
