latch1.v
module latch1(load, d,q);
  input load;
  input[1:0] d;
  output[1:0] q;

  reg[1:0] q;
  
  always @(load or d)
    begin
      if (load)
        q = d;
    end
endmodule

latch1_test.v
module latch1_test;
  reg load;
  reg[1:0] d;

  // output declaration of module latch1
  wire [1:0] q;

  latch1 u_latch1(
           .load 	(load  ),
           .d    	(d     ),
           .q    	(q     )
         );
  initial
    begin
      load=0;
      forever
        #1 load = ~load;

    end

  initial
    begin
      d = 3;
      #10 $finish();

    end

  initial
    begin
      $dumpfile("latch1_wave.vcd");
      $dumpvars(0, latch1_test);
    end

endmodule

latch1_wave.vcd
$date
	Mon May 19 11:40:01 2025
$end
$version
	Icarus Verilog
$end
$timescale
	1s
$end
$scope module latch1_test $end
$var wire 2 ! q [1:0] $end
$var reg 2 " d [1:0] $end
$var reg 1 # load $end
$scope module u_latch1 $end
$var wire 2 $ d [1:0] $end
$var wire 1 # load $end
$var reg 2 % q [1:0] $end
$upscope $end
$upscope $end
$enddefinitions $end
$comment Show the parameter values. $end
$dumpall
$end
#0
$dumpvars
bx %
b11 $
0#
b11 "
bx !
$end
#1
b11 !
b11 %
1#
#2
0#
#3
1#
#4
0#
#5
1#
#6
0#
#7
1#
#8
0#
#9
1#
#10
0#
