latch2.v
module latch2(load, a, b,q);
  input load;
  input[1:0] a,b ;
  output[1:0] q;

  reg[1:0] q;
  always @(load or a or b)
    begin
      if (load)
        q = a;
      else
        q = b;
    end
endmodule

latch2_test.v
module latch2_test;
  reg load;
  reg[1:0] a,b;

  // output declaration of module latch2
  wire [1:0] q;

  latch2 u_latch2(
           .load 	(load  ),
           .a    	(a     ),
           .b    	(b     ),
           .q    	(q     )
         );
  initial
    begin
      load=0;
      forever
        #1 load = ~load;

    end

  initial
    begin
      a = 3;
      b = 2;
      #10 $finish();

    end

  initial
    begin
      $dumpfile("latch2_wave.vcd");
      $dumpvars(0, latch2_test);
    end

endmodule

latch2_wave.vcd
$date
	Mon May 19 11:40:38 2025
$end
$version
	Icarus Verilog
$end
$timescale
	1s
$end
$scope module latch2_test $end
$var wire 2 ! q [1:0] $end
$var reg 2 " a [1:0] $end
$var reg 2 # b [1:0] $end
$var reg 1 $ load $end
$scope module u_latch2 $end
$var wire 2 % a [1:0] $end
$var wire 2 & b [1:0] $end
$var wire 1 $ load $end
$var reg 2 ' q [1:0] $end
$upscope $end
$upscope $end
$enddefinitions $end
$comment Show the parameter values. $end
$dumpall
$end
#0
$dumpvars
b10 '
b10 &
b11 %
0$
b10 #
b11 "
b10 !
$end
#1
b11 !
b11 '
1$
#2
b10 !
b10 '
0$
#3
b11 !
b11 '
1$
#4
b10 !
b10 '
0$
#5
b11 !
b11 '
1$
#6
b10 !
b10 '
0$
#7
b11 !
b11 '
1$
#8
b10 !
b10 '
0$
#9
b11 !
b11 '
1$
#10
b10 !
b10 '
0$
