non_blocking.v
module non_blocking(clk, a,b,c,d);
  input clk, a;
  output[3:0] b, c, d;
  reg[3:0] b, c, d;
  always @(posedge clk)
    begin
      b <= a;
      c <= b;
      d <= c;
    end

endmodule

non_blocking_test.v
`timescale 1ns/1ps

module non_blocking_test;
  reg clk, a;
  wire [3:0] b, c, d;

  // 實例化測試模組
  non_blocking u_non_blocking(
                 .clk 	(clk  ),
                 .a   	(a    ),
                 .b   	(b    ),
                 .c   	(c    ),
                 .d   	(d    )
               );

  // 時脈產生器 (20ns 週期)
  initial
    begin
      clk = 0;
      forever
        #10 clk = ~clk;
    end

  // 輸入訊號 a 隨時間變化
  initial
    begin
      a = 0;
      #25 a = 1;
      #20 a = 2;
      #20 a = 3;
      #20 a = 4;
      #20 $finish;
    end

  // 顯示輸出結果
  initial
    begin
      $monitor("Time=%0t | clk=%b | a=%b | b=%d | c=%d | d=%d",
               $time, clk, a, b, c, d);
    end

  // 波形輸出設定
  initial
    begin
      $dumpfile("non_blocking_wave.vcd");
      $dumpvars(0, non_blocking_test);
    end
endmodule

non_blocking_wave.vcd
$date
	Sat May 17 16:49:00 2025
$end
$version
	Icarus Verilog
$end
$timescale
	1ps
$end
$scope module non_blocking_test $end
$var wire 4 ! d [3:0] $end
$var wire 4 " c [3:0] $end
$var wire 4 # b [3:0] $end
$var reg 1 $ a $end
$var reg 1 % clk $end
$scope module u_non_blocking $end
$var wire 1 $ a $end
$var wire 1 % clk $end
$var reg 4 & b [3:0] $end
$var reg 4 ' c [3:0] $end
$var reg 4 ( d [3:0] $end
$upscope $end
$upscope $end
$enddefinitions $end
$comment Show the parameter values. $end
$dumpall
$end
#0
$dumpvars
bx (
bx '
bx &
0%
0$
bx #
bx "
bx !
$end
#10000
b0 #
b0 &
1%
#20000
0%
#25000
1$
#30000
b0 "
b0 '
b1 #
b1 &
1%
#40000
0%
#45000
0$
#50000
b0 !
b0 (
b1 "
b1 '
b0 #
b0 &
1%
#60000
0%
#65000
1$
#70000
b1 !
b1 (
b0 "
b0 '
b1 #
b1 &
1%
#80000
0%
#85000
0$
#90000
b0 !
b0 (
b1 "
b1 '
b0 #
b0 &
1%
